{
    "version": "https://jsonfeed.org/version/1",
    "title": "Florence的城堡 • All posts by \"typescript\" category",
    "description": "我在这里随便写写",
    "home_page_url": "http://example.com",
    "items": [
        {
            "id": "http://example.com/2023/01/13/%E5%89%8D%E7%AB%AF%E7%9A%84%E4%B8%A2%E4%BA%BA%E7%AC%94%E8%AE%B0/Typescript/Typescript/",
            "url": "http://example.com/2023/01/13/%E5%89%8D%E7%AB%AF%E7%9A%84%E4%B8%A2%E4%BA%BA%E7%AC%94%E8%AE%B0/Typescript/Typescript/",
            "title": "Typescript",
            "date_published": "2023-01-13T07:38:53.914Z",
            "content_html": "<p>来早了，先去<span class=\"exturl\" data-url=\"aHR0cHM6Ly93d3cudHlwZXNjcmlwdGxhbmcub3JnLw==\">官网</span>看看？</p>\n",
            "tags": []
        }
    ]
}